blitzmeets/__init__.py
blitzmeets/client.py
blitzmeets-0.1.1.dist-info/METADATA
blitzmeets-0.1.1.dist-info/WHEEL
blitzmeets-0.1.1.dist-info/top_level.txt
blitzmeets-0.1.1.dist-info/RECORD
