Metadata-Version: 2.1
Name: blitzmeets
Version: 0.1.1
Summary: A utility to create virtual meetings programatically
Home-page: https://github.com/BliyzJB/BlitzMeets
Author: Your Name
Author-email: youremail@example.com
Classifier: Development Status :: 3 - Alpha
Classifier: License :: OSI Approved :: MIT License
Classifier: Programming Language :: Python :: 3
Classifier: Programming Language :: Python :: 3.6
Classifier: Programming Language :: Python :: 3.7
Classifier: Programming Language :: Python :: 3.8
Classifier: Programming Language :: Python :: 3.9
Classifier: Topic :: Software Development :: Libraries :: Python Modules
Requires-Dist: requests
Requires-Dist: qrcode
